{
  "host": "localhost",
  "port": 3030,
  "public": "../public/",
  "paginate": {
    "default": 10,
    "max": 50
  },
  "mongodb": "mongodb+srv://intern:qvG5DLEivlS49Sa5@cluster-staging-repzo-1.yrmdo.mongodb.net/staging-1db",
  "authentication": {
    "entity": "user",
    "service": "users",
    "secret": "ww2fwn8cDWn/+v8WOIuATpn6b00=",
    "authStrategies": [
      "jwt",
      "local"
    ],
    "jwtOptions": {
      "header": {
        "typ": "access"
      },
      "audience": "https://yourdomain.com",
      "issuer": "feathers",
      "algorithm": "HS256",
      "expiresIn": "1d"
    },
    "local": {
      "usernameField": "email",
      "passwordField": "password"
    }
  }
}
